{
    "第八章判断主菜单": {
        "recognition": "OCR",
        "expected": "礼包",
        "roi": [
            895,
            619,
            58,
            70
        ],
        "next": [
            "第八章进入卡带"
        ],
        "on_error": [
            "主返回菜单"
        ]
    },
    "第八章进入卡带": {
        "recognition": "OCR",
        "expected": "礼包",
        "roi": [
            895,
            619,
            58,
            70
        ],
        "action": "Click",
        "target": [
            1119,
            639,
            1,
            1
        ],
        "next": [
            "第八章向上划动游戏卡"
        ],
        "on_error": [
            "主返回菜单"
        ]
    },
    "第八章向上划动游戏卡": {
        "recognition": "OCR",
        "expected": "游戏卡珍藏集",
        "roi": [
            10,
            6,
            375,
            73
        ],
        "action": "Swipe",
        "begin": [
            659,
            116,
            1,
            1
        ],
        "end": [
            659,
            623,
            1,
            1
        ],
        "next": [
            "第八章向左划动游戏卡1"
        ],
        "on_error": [
            "主返回菜单"
        ],
        "post_delay": 4000
    },
    "第八章向左划动游戏卡1": {
        "recognition": "OCR",
        "expected": "剧情游戏卡",
        "roi": [
            108,
            93,
            179,
            44
        ],
        "action": "Swipe",
        "begin": [
            169,
            210,
            1,
            1
        ],
        "end": [
            1142,
            210,
            1,
            1
        ],
        "next": [
            "第八章向左划动游戏卡2"
        ],
        "on_error": [
            "主返回菜单"
        ],
        "post_delay": 4000
    },
    "第八章向左划动游戏卡2": {
        "roi": [
            108,
            93,
            179,
            44
        ],
        "action": "Swipe",
        "begin": [
            336,
            210,
            1,
            1
        ],
        "end": [
            911,
            210,
            1,
            1
        ],
        "next": [
            "第八章向右划动游戏卡1"
        ],
        "on_error": [
            "主返回菜单"
        ],
        "post_delay": 4000
    },
    "第八章向右划动游戏卡1": {
        "action": "Swipe",
        "begin": [
            962,
            213,
            1,
            1
        ],
        "end": [
            551,
            213,
            1,
            1
        ],
        "next": [
            "进入第八章卡带"
        ],
        "on_error": [
             "主返回菜单"
        ],
        "post_delay": 4000
    },
    "进入第八章卡带": {
        "recognition": "TemplateMatch",
        "template": "第八章/第八章.png",
        "action": "Click",
        "next": [
            "打开第八章地图1"
        ],
        "on_error": [
            "主返回菜单"
        ]
    },
    "打开第八章地图1": {
        "recognition": "TemplateMatch",
        "template": "副本.png",
        "action": "Click",
        "target": [
            880,
            568,
            1,
            1
        ],
        "next": [
            "第八章判断地图位置"
        ]
    },
    "第八章判断地图位置": {
        "timeout": 500,
        "inverse": true,
        "recognition": "TemplateMatch",
        "template": "第八章/第八章地图位置.png",
        "roi": [
            389,
            597,
            501,
            100
        ],
        "next": [
            "第八章向左切换地图1"
        ],
        "on_error": [
            "第八章关闭地图1"
        ]
    },
    "第八章关闭地图1": {
        "recognition": "OCR",
        "expected": "移动魔法阵",
        "roi": [
            152,
            11,
            189,
            60
        ],
        "action": "Click",
        "target": [
            102,
            36,
            3,
            5
        ],
        "next": [
            "第八章探查"
        ],
        "on_error": [
            "主返回菜单"
        ]
    },
    "第八章向左切换地图1": {
        "recognition": "OCR",
        "expected": "移动魔法阵",
        "roi": [
            152,
            11,
            189,
            60
        ],
        "action": "Click",
        "target": [
            303,
            343,
            1,
            1
        ],
        "next": [
            "第八章向左切换地图2"
        ]
    },
    "第八章向左切换地图2": {
        "recognition": "OCR",
        "expected": "移动魔法阵",
        "roi": [
            152,
            11,
            189,
            60
        ],
        "action": "Click",
        "target": [
            303,
            343,
            1,
            1
        ],
        "next": [
            "第八章向左切换地图3"
        ]
    },
    "第八章向左切换地图3": {
        "recognition": "OCR",
        "expected": "移动魔法阵",
        "roi": [
            152,
            11,
            189,
            60
        ],
        "action": "Click",
        "target": [
            303,
            343,
            1,
            1
        ],
        "next": [
            "第八章向左切换地图4"
        ]
    },
    "第八章向左切换地图4": {
        "recognition": "OCR",
        "expected": "移动魔法阵",
        "roi": [
            152,
            11,
            189,
            60
        ],
        "action": "Click",
        "target": [
            303,
            343,
            1,
            1
        ],
        "next": [
            "第八章传送1"
        ]
    },
    "第八章传送1": {
        "recognition": "TemplateMatch",
        "template": "传送点.png",
        "green_mask": true,
        "action": "Click",
        "pre_delay": 1000,
        "next": [
            "第八章探查"
        ]
    },
    "第八章探查": {
        "recognition": "TemplateMatch",
        "template": "副本.png",
        "action": "Click",
        "target": [
            1014,
            649,
            1,
            1
        ],
        "post_delay": 3000,
        "next": [
            "第八章吸收1"
        ]
    },
    "第八章吸收1": {
        "recognition": "TemplateMatch",
        "template": "副本.png",
        "action": "Click",
        "roi": [
            79,
            144,
            81,
            83
        ],
        "target": [
            975,
            562,
            1,
            1
        ],
        "post_delay": 3000,
        "next": [
            "打开第八章地图2"
        ]
    },
    "打开第八章地图2": {
        "recognition": "TemplateMatch",
        "template": "副本.png",
        "action": "Click",
        "target": [
            880,
            568,
            1,
            1
        ],
        "next": [
            "第八章向右切换地图1"
        ]
    },
    "第八章向右切换地图1": {
        "recognition": "OCR",
        "expected": "移动魔法阵",
        "roi": [
            152,
            11,
            189,
            60
        ],
        "action": "Click",
        "target": [
            975,
            342,
            1,
            1
        ],
        "next": [
            "第八章传送2"
        ]
    },
    "第八章传送2": {
        "recognition": "TemplateMatch",
        "template": "传送点.png",
        "green_mask": true,
        "action": "Click",
        "pre_delay": 1000,
        "next": [
            "第八章吸收2"
        ]
    },
    "第八章吸收2": {
        "recognition": "TemplateMatch",
        "template": "副本.png",
        "action": "Click",
        "roi": [
            79,
            144,
            81,
            83
        ],
        "target": [
            975,
            562,
            1,
            1
        ],
        "post_delay": 3000,
        "next": [
            "第八章召集1"
        ]
    },
    "第八章召集1": {
        "recognition": "TemplateMatch",
        "template": "副本.png",
        "action": "Click",
        "target": [
            1098,
            445,
            1,
            1
        ],
        "post_delay": 3000,
        "next": [
            "打开第八章地图3"
        ]
    },
    "打开第八章地图3": {
        "recognition": "TemplateMatch",
        "template": "副本.png",
        "action": "Click",
        "target": [
            880,
            568,
            1,
            1
        ],
        "next": [
            "第八章向右切换地图2"
        ]
    },
    "第八章向右切换地图2": {
        "recognition": "OCR",
        "expected": "移动魔法阵",
        "roi": [
            152,
            11,
            189,
            60
        ],
        "action": "Click",
        "target": [
            975,
            342,
            1,
            1
        ],
        "next": [
            "第八章传送3"
        ]
    },
    "第八章传送3": {
        "recognition": "TemplateMatch",
        "template": "传送点.png",
        "green_mask": true,
        "action": "Click",
        "pre_delay": 1000,
        "next": [
            "第八章吸收3"
        ]
    },
    "第八章吸收3": {
        "recognition": "TemplateMatch",
        "template": "副本.png",
        "action": "Click",
        "roi": [
            79,
            144,
            81,
            83
        ],
        "target": [
            1014,
            482,
            1,
            1
        ],
        "post_delay": 3000,
        "next": [
            "第八章召集2"
        ]
    },
    "第八章召集2": {
        "recognition": "TemplateMatch",
        "template": "副本.png",
        "action": "Click",
        "target": [
            1098,
            445,
            1,
            1
        ],
        "post_delay": 3000,
        "next": [
            "主返回菜单"
        ]
    }
}